yara.cpython-312-i386-linux-musl.so
yara_python_wheel-4.4.0.dist-info/WHEEL
yara_python_wheel-4.4.0.dist-info/LICENSE
yara_python_wheel-4.4.0.dist-info/RECORD
yara_python_wheel-4.4.0.dist-info/top_level.txt
yara_python_wheel-4.4.0.dist-info/METADATA
yara_python_wheel.libs/libcrypto-ece57400.so.1.1
