Metadata-Version: 2.1
Name: yara-python-wheel
Version: 4.4.0
Summary: Python interface for YARA
Home-page: https://github.com/Schamper/yara-python-wheel
Author: Victor M. Alvarez
Author-email: plusvic@gmail.com, vmalvarez@virustotal.com
License: Apache 2.0
Classifier: Programming Language :: Python
Classifier: License :: OSI Approved :: Apache Software License
Classifier: Operating System :: OS Independent
Classifier: Development Status :: 5 - Production/Stable
License-File: LICENSE
